cfnow/__init__.py
cfnow/_cf_searchers.py
cfnow/_checkers.py
cfnow/_data_standardizer.py
cfnow/_fine_tune.py
cfnow/_img_segmentation.py
cfnow/_model_standardizer.py
cfnow/_obj_functions.py
cfnow/cf_finder.py
cfnow/assets/verb_tenses.pkl
tests/__init__.py
tests/test__cf_searchers.py
tests/test__checkers.py
tests/test__data_standardizer.py
tests/test__fine_tune.py
tests/test__img_segmentation.py
tests/test__model_standardizer.py
tests/test__obj_functions.py
tests/test_cf_finder.py
cfnow-0.0.6.dist-info/LICENSE.txt
cfnow-0.0.6.dist-info/METADATA
cfnow-0.0.6.dist-info/WHEEL
cfnow-0.0.6.dist-info/top_level.txt
cfnow-0.0.6.dist-info/RECORD
