Metadata-Version: 2.1
Name: cfnow
Version: 0.0.6
Summary: Generate counterfactuals with ease. This package takes a model and point (with a certain class) and minimally changes it to flip the classification result.
Home-page: https://github.com/rmazzine/CFNOW
Author: Raphael Mazzine Barbosa de Oliveira
Author-email: mazzine.r@gmail.com
License: MIT
Download-URL: https://pypi.org/project/cfnow/
Keywords: counterfactuals,counterfactual explanations,flipping original class,explainable artificial intelligence
Platform: UNKNOWN
Classifier: Intended Audience :: Developers
Classifier: License :: OSI Approved :: MIT License
Classifier: Natural Language :: English
Classifier: Programming Language :: Python :: 3
Requires-Dist: numpy
Requires-Dist: pandas
Requires-Dist: scikit-learn
Requires-Dist: scikit-image
Requires-Dist: opencv-python
Requires-Dist: nltk
Requires-Dist: counterplots
